LICENSE
MANIFEST.in
README.md
setup.cfg
setup.py
config/sqlite/example.conf
mqttstore/__init__.py
mqttstore/__main__.py
mqttstore/queue.py
mqttstore/sqlite.py
mqttstore/version.py
mqttstore.egg-info/PKG-INFO
mqttstore.egg-info/SOURCES.txt
mqttstore.egg-info/dependency_links.txt
mqttstore.egg-info/entry_points.txt
mqttstore.egg-info/requires.txt
mqttstore.egg-info/top_level.txt
mqttstore/cli/__init__.py
mqttstore/cli/__main__.py
mqttstore/cli/commands/__init__.py
mqttstore/cli/commands/main.py
mqttstore/cli/commands/sqlite/__init__.py
mqttstore/cli/commands/sqlite/client.py
mqttstore/cli/commands/sqlite/config.py
systemd/mqttstore.service