Metadata-Version: 2.1
Name: mqttstore
Version: 0.3.0
Summary: Storing MQTT data into an SQL
Home-page: https://gitlab.com/tue-umphy/co2mofetten/python3-mqttstore
Author: Yann Buechau
Author-email: nobodyinperson@gmx.de
License: GPLv3
Keywords: mqtt,sql,sqlite
Platform: UNKNOWN
Classifier: License :: OSI Approved :: GNU General Public License v3 (GPLv3)
Classifier: Programming Language :: Python :: 3.4
Classifier: Programming Language :: Python :: 3.5
Classifier: Programming Language :: Python :: 3.6
Classifier: Programming Language :: Python :: 3.7
Classifier: Intended Audience :: Science/Research
Classifier: Topic :: Scientific/Engineering
Classifier: Development Status :: 4 - Beta
Requires-Python: >= 3.4
